forecastpy/__init__.py
forecastpy/forecast.py
forecastpy-1.1.0.dist-info/LICENSE
forecastpy-1.1.0.dist-info/METADATA
forecastpy-1.1.0.dist-info/WHEEL
forecastpy-1.1.0.dist-info/top_level.txt
forecastpy-1.1.0.dist-info/RECORD
