Metadata-Version: 2.1
Name: forecastpy
Version: 1.1.0
Summary: A python package to interact with the OpenWeatherAPI in a simple and fast way.
Home-page: https://github.com/devmatteini/forecastpy
Author: Cosimo Matteini
Author-email: dev.matteini@gmail.com
License: UNKNOWN
Keywords: weather forecast openweathermap
Platform: UNKNOWN
Classifier: Development Status :: 4 - Beta
Classifier: Programming Language :: Python :: 3.7
Classifier: License :: OSI Approved :: GNU General Public License v3 (GPLv3)
Classifier: Operating System :: OS Independent
Requires-Dist: requests
